{
  "menu": [
    {
      "img": "img/tabs/vegy.jpg",
      "altimg": "vegy",
      "title": "Меню 'Фитнес'",
      "descr": "Меню 'Фитнес' - это новый подход к приготовлению блюд: больше свежих овощей и фруктов. Продукт активных и здоровых людей. Это абсолютно новый продукт с оптимальной ценой и высоким качеством!",
      "price": 12,
      "id": "6006"
    },
    {
      "img": "img/tabs/elite.jpg",
      "altimg": "elite",
      "title": "Меню 'Премиум'",
      "descr": "В меню 'Премиум' мы используем не только красивый дизайн упаковки, но и качественное исполнение блюд. Красная рыба, морепродукты, фрукты - ресторанное меню без похода в ресторан! Попробуйте обязательно!",
      "price": 21,
      "id": "ac11"
    },
    {
      "img": "img/tabs/post.jpg",
      "altimg": "post",
      "title": "Меню 'Постное'",
      "descr": "Меню 'Постное' - это тщательный подбор ингредиентов: полное отсутствие продуктов животного происхождения, молоко из миндаля, овса, кокоса или гречки, правильное количество белков за счет тофу и импортных вегетарианских стейков.",
      "price": 16,
      "id": "68b0"
    }
  ],
  "requests": [
    {
      "id": "6c1c",
      "name": "Илья",
      "phone": "+7 910 000 87 50"
    },
    {
      "id": "0de0",
      "name": "Илья",
      "phone": "+7 (910) 000-87-50"
    },
    {
      "id": "5143",
      "name": "Илья",
      "phone": "+7 910 000 87 50"
    },
    {
      "id": "173d",
      "name": "Илья",
      "phone": "+7 910 000 87 50"
    },
    {
      "id": "eeca",
      "name": "Илья",
      "phone": "+7 910 000 87 50"
    },
    {
      "id": "b423",
      "name": "Илья",
      "phone": "+7 910 000 87 50"
    },
    {
      "id": "c17d",
      "name": "Илья",
      "phone": "+7 910 000 87 50"
    },
    {
      "id": "e2f1",
      "name": "Илья",
      "phone": "+7 910 000 87 50"
    },
    {
      "id": "27bc",
      "name": "Илья",
      "phone": "+7 910 000 87 50"
    }
  ]
}